tg_parser/__init__.py
tg_parser/__main__.py
tg_parser/py.typed
tg_parser/application/__init__.py
tg_parser/application/use_cases/__init__.py
tg_parser/application/use_cases/chunk_chat.py
tg_parser/application/use_cases/get_mentions.py
tg_parser/application/use_cases/get_statistics.py
tg_parser/application/use_cases/parse_chat.py
tg_parser/domain/__init__.py
tg_parser/domain/constants.py
tg_parser/domain/exceptions.py
tg_parser/domain/entities/__init__.py
tg_parser/domain/entities/chat.py
tg_parser/domain/entities/chunk.py
tg_parser/domain/entities/message.py
tg_parser/domain/entities/participant.py
tg_parser/domain/entities/topic.py
tg_parser/domain/protocols/__init__.py
tg_parser/domain/protocols/chunker.py
tg_parser/domain/protocols/filter.py
tg_parser/domain/protocols/reader.py
tg_parser/domain/protocols/writer.py
tg_parser/domain/value_objects/__init__.py
tg_parser/domain/value_objects/config_settings.py
tg_parser/domain/value_objects/date_range.py
tg_parser/domain/value_objects/filter_spec.py
tg_parser/domain/value_objects/identifiers.py
tg_parser/infrastructure/__init__.py
tg_parser/infrastructure/chunkers/__init__.py
tg_parser/infrastructure/chunkers/fixed_chunker.py
tg_parser/infrastructure/chunkers/hybrid_chunker.py
tg_parser/infrastructure/chunkers/topic_chunker.py
tg_parser/infrastructure/config/__init__.py
tg_parser/infrastructure/config/config_loader.py
tg_parser/infrastructure/config/config_reader.py
tg_parser/infrastructure/config/mcp_config_manager.py
tg_parser/infrastructure/filters/__init__.py
tg_parser/infrastructure/filters/composite.py
tg_parser/infrastructure/filters/date_filter.py
tg_parser/infrastructure/filters/sender_filter.py
tg_parser/infrastructure/filters/topic_filter.py
tg_parser/infrastructure/readers/__init__.py
tg_parser/infrastructure/readers/_parsing.py
tg_parser/infrastructure/readers/telegram_json.py
tg_parser/infrastructure/readers/telegram_stream.py
tg_parser/infrastructure/token_counters/__init__.py
tg_parser-1.2.0.dist-info/METADATA
tg_parser-1.2.0.dist-info/WHEEL
tg_parser-1.2.0.dist-info/entry_points.txt
tg_parser-1.2.0.dist-info/licenses/LICENSE
tg_parser-1.2.0.dist-info/RECORD
