Metadata-Version: 2.4
Name: tg-parser
Version: 1.2.0
Summary: Parse Telegram Desktop JSON exports for LLM processing
Project-URL: Homepage, https://github.com/mdemyanov/tg-parser
Project-URL: Repository, https://github.com/mdemyanov/tg-parser
Project-URL: Issues, https://github.com/mdemyanov/tg-parser/issues
Project-URL: Changelog, https://github.com/mdemyanov/tg-parser/blob/main/CHANGELOG.md
Author-email: Maxim Demyanov <mdemyanov@naumen.ru>
License: MIT
License-File: LICENSE
Keywords: cli,llm,mcp,parser,telegram
Classifier: Development Status :: 5 - Production/Stable
Classifier: Environment :: Console
Classifier: Intended Audience :: Developers
Classifier: License :: OSI Approved :: MIT License
Classifier: Programming Language :: Python :: 3.11
Classifier: Programming Language :: Python :: 3.12
Classifier: Topic :: Communications :: Chat
Classifier: Typing :: Typed
Requires-Python: >=3.11
Requires-Dist: mcp>=1.25.0
Requires-Dist: pydantic-settings>=2.0.0
Requires-Dist: pydantic>=2.0.0
Requires-Dist: rich>=13.0.0
Requires-Dist: typer>=0.9.0
Provides-Extra: all
Requires-Dist: ijson>=3.2.0; extra == 'all'
Requires-Dist: mcp>=1.0.0; extra == 'all'
Requires-Dist: tiktoken>=0.5.0; extra == 'all'
Provides-Extra: dev
Requires-Dist: pyright>=1.1.0; extra == 'dev'
Requires-Dist: pytest-asyncio>=0.23.0; extra == 'dev'
Requires-Dist: pytest-cov>=4.0.0; extra == 'dev'
Requires-Dist: pytest>=8.0.0; extra == 'dev'
Requires-Dist: ruff>=0.1.0; extra == 'dev'
Provides-Extra: mcp
Requires-Dist: mcp>=1.0.0; extra == 'mcp'
Provides-Extra: streaming
Requires-Dist: ijson>=3.2.0; extra == 'streaming'
Provides-Extra: tiktoken
Requires-Dist: tiktoken>=0.5.0; extra == 'tiktoken'
